[
  {
    "platform":"DMart",
    "product":"Tata Salt Lite - Low Sodium Iodised ",
    "brand":"Tata",
    "mrp":50.0,
    "offer_price":42.0,
    "quantity":"1 kg",
    "delivery_time":"4PM-6PM"
  },
  {
    "platform":"BlinkIt",
    "product":"Tata Salt Lite (15% Less Sodium)",
    "brand":"Tata",
    "mrp":50.0,
    "offer_price":50.0,
    "quantity":"1 kg",
    "delivery_time":"11 Mins"
  },
  {
    "platform":"Zepto",
    "product":"By Nature Himalayan Pink Salt Salt In Fresh Mineral Rich Low Sodium Pink Salt Flavorful Vegan Food",
    "brand":"By Nature",
    "mrp":160.0,
    "offer_price":148.0,
    "quantity":"400 g",
    "delivery_time":"9 Mins"
  },
  {
    "platform":"Swiggy",
    "product":"Tata Low Sodium Lite Salt",
    "brand":"Tata",
    "mrp":50.0,
    "offer_price":50.0,
    "quantity":"1 kg",
    "delivery_time":"14 Mins"
  },
  {
    "platform":"DMart",
    "product":"Tata SuperLite Salt ",
    "brand":"Tata",
    "mrp":75.0,
    "offer_price":65.0,
    "quantity":"1 kg",
    "delivery_time":"4PM-6PM"
  },
  {
    "platform":"BlinkIt",
    "product":"Tata Salt Superlite (30% Less Sodium)",
    "brand":"Tata",
    "mrp":75.0,
    "offer_price":73.0,
    "quantity":"1 kg",
    "delivery_time":"11 Mins"
  },
  {
    "platform":"Zepto",
    "product":"Tata Salt Superlite With 30% Low Sodium",
    "brand":"Tata",
    "mrp":75.0,
    "offer_price":75.0,
    "quantity":"",
    "delivery_time":"9 Mins"
  },
  {
    "platform":"BlinkIt",
    "product":"Aashirvaad Proactive Salt Lite",
    "brand":"Aashirvaad",
    "mrp":50.0,
    "offer_price":46.0,
    "quantity":"1 kg",
    "delivery_time":"11 Mins"
  },
  {
    "platform":"Zepto",
    "product":"Tata Himalayan Rock Pink Salt Pouch, Premium Sendha Namak, With Natural Trace Minerals, Low Sodium, Crystal Salt",
    "brand":"Tata",
    "mrp":120.0,
    "offer_price":113.0,
    "quantity":"1 kg",
    "delivery_time":"9 Mins"
  },
  {
    "platform":"DMart",
    "product":"Epigamia Low Fat Greek Yogurt Natural ",
    "brand":"Epigamia",
    "mrp":60.0,
    "offer_price":45.0,
    "quantity":"85 g",
    "delivery_time":"4PM-6PM"
  },
  {
    "platform":"Swiggy",
    "product":"Tata Salt Rock Salt Pouch",
    "brand":"Tata",
    "mrp":120.0,
    "offer_price":113.0,
    "quantity":"1 kg",
    "delivery_time":"14 Mins"
  },
  {
    "platform":"BlinkIt",
    "product":"Whole Farm Premium Powder Black Salt (Kala Namak)",
    "brand":"Whole Farm",
    "mrp":40.0,
    "offer_price":15.0,
    "quantity":"200 g",
    "delivery_time":"11 Mins"
  },
  {
    "platform":"Zepto",
    "product":"Tata Himalayan Rock Pink Salt Pouch, Premium Sendha Namak, With Natural Trace Minerals, Low Sodium, Crystal Salt",
    "brand":"Tata",
    "mrp":65.0,
    "offer_price":58.0,
    "quantity":"500 g",
    "delivery_time":"9 Mins"
  },
  {
    "platform":"DMart",
    "product":"Epigamia Low Fat Greek Yogurt Strawberry ",
    "brand":"Epigamia",
    "mrp":60.0,
    "offer_price":45.0,
    "quantity":"85 g",
    "delivery_time":"4PM-6PM"
  },
  {
    "platform":"Swiggy",
    "product":"Tata Iodized Salt",
    "brand":"Tata",
    "mrp":30.0,
    "offer_price":27.0,
    "quantity":"1 kg",
    "delivery_time":"14 Mins"
  },
  {
    "platform":"Swiggy",
    "product":"Puro Healthy Salt",
    "brand":"Puro",
    "mrp":115.0,
    "offer_price":107.0,
    "quantity":"1 kg",
    "delivery_time":"14 Mins"
  },
  {
    "platform":"BlinkIt",
    "product":"Puro Healthy Rock Salt (Sendha Namak)",
    "brand":"Puro",
    "mrp":115.0,
    "offer_price":112.0,
    "quantity":"1 kg",
    "delivery_time":"11 Mins"
  },
  {
    "platform":"Zepto",
    "product":"Tata Salt Lite | 15% Low Sodium Iodized Salt",
    "brand":"Tata",
    "mrp":50.0,
    "offer_price":50.0,
    "quantity":"1 kg",
    "delivery_time":"9 Mins"
  },
  {
    "platform":"DMart",
    "product":"Epigamia Low Fat Greek Yogurt Wild Raspberry ",
    "brand":"Epigamia",
    "mrp":60.0,
    "offer_price":45.0,
    "quantity":"85 g",
    "delivery_time":"4PM-6PM"
  },
  {
    "platform":"Swiggy",
    "product":"By Nature Himalayan Pink Salt",
    "brand":"By Nature",
    "mrp":160.0,
    "offer_price":136.0,
    "quantity":"400 g",
    "delivery_time":"14 Mins"
  },
  {
    "platform":"BlinkIt",
    "product":"Whole Farm Premium Black Salt (Kala Namak)",
    "brand":"Whole Farm",
    "mrp":20.0,
    "offer_price":11.0,
    "quantity":"100 g",
    "delivery_time":"11 Mins"
  },
  {
    "platform":"Zepto",
    "product":"Puro Healthy Salt",
    "brand":"Puro",
    "mrp":115.0,
    "offer_price":115.0,
    "quantity":"1 kg",
    "delivery_time":"9 Mins"
  },
  {
    "platform":"DMart",
    "product":"Epigamia Low Fat Greek Yogurt Alphonso Mango ",
    "brand":"Epigamia",
    "mrp":60.0,
    "offer_price":45.0,
    "quantity":"85 g",
    "delivery_time":"4PM-6PM"
  },
  {
    "platform":"Swiggy",
    "product":"By Nature Himalayan Pink Salt",
    "brand":"By Nature",
    "mrp":320.0,
    "offer_price":269.0,
    "quantity":"400 g x 2",
    "delivery_time":"14 Mins"
  },
  {
    "platform":"Swiggy",
    "product":"organic tattva Rock Salt",
    "brand":"organic tattva",
    "mrp":60.0,
    "offer_price":53.0,
    "quantity":"500 g",
    "delivery_time":"14 Mins"
  },
  {
    "platform":"BlinkIt",
    "product":"Natural Tattva Rock Salt \/ Sendha Namak",
    "brand":"Natural Tattva",
    "mrp":60.0,
    "offer_price":56.0,
    "quantity":"500 g",
    "delivery_time":"11 Mins"
  },
  {
    "platform":"DMart",
    "product":"Epigamia Low Fat Greek Yogurt Blueberry ",
    "brand":"Epigamia",
    "mrp":60.0,
    "offer_price":45.0,
    "quantity":"85 g",
    "delivery_time":"4PM-6PM"
  },
  {
    "platform":"DMart",
    "product":"Makhanawala's Himalayan Pink Salt Makhana ",
    "brand":"Makhanawala's",
    "mrp":120.0,
    "offer_price":60.0,
    "quantity":"28 g",
    "delivery_time":"4PM-6PM"
  },
  {
    "platform":"Swiggy",
    "product":"Aashirvaad Himalayan Pink Salt",
    "brand":"Aashirvaad",
    "mrp":120.0,
    "offer_price":105.0,
    "quantity":"1 kg",
    "delivery_time":"14 Mins"
  },
  {
    "platform":"BlinkIt",
    "product":"Aashirvaad Himalayan Pink Salt",
    "brand":"Aashirvaad",
    "mrp":120.0,
    "offer_price":105.0,
    "quantity":"1 kg",
    "delivery_time":"11 Mins"
  },
  {
    "platform":"DMart",
    "product":"Tata Salt - Evaporated Iodised ",
    "brand":"Tata",
    "mrp":30.0,
    "offer_price":27.0,
    "quantity":"1 kg",
    "delivery_time":"4PM-6PM"
  },
  {
    "platform":"Swiggy",
    "product":"Supreme Harvest Rock Salt",
    "brand":"Supreme Harvest",
    "mrp":130.0,
    "offer_price":125.0,
    "quantity":"1 kg",
    "delivery_time":"14 Mins"
  },
  {
    "platform":"BlinkIt",
    "product":"Whole Farm Premium Rock Salt \/ Sendha Namak Powder (Sendha Namak)",
    "brand":"Whole Farm",
    "mrp":40.0,
    "offer_price":25.0,
    "quantity":"200 g",
    "delivery_time":"11 Mins"
  },
  {
    "platform":"DMart",
    "product":"Tata Rock Salt Powder Pouch ",
    "brand":"Tata",
    "mrp":65.0,
    "offer_price":58.0,
    "quantity":"500 gm",
    "delivery_time":"4PM-6PM"
  },
  {
    "platform":"BlinkIt",
    "product":"Organic India Himalayan Organic Pink Salt",
    "brand":"Organic India",
    "mrp":150.0,
    "offer_price":150.0,
    "quantity":"1 kg",
    "delivery_time":"11 Mins"
  },
  {
    "platform":"DMart",
    "product":"Aashirvaad Salt ",
    "brand":"Aashirvaad",
    "mrp":30.0,
    "offer_price":19.0,
    "quantity":"1 kg",
    "delivery_time":"4PM-6PM"
  },
  {
    "platform":"Swiggy",
    "product":"Aashirvaad Iodised Salt",
    "brand":"Aashirvaad",
    "mrp":30.0,
    "offer_price":24.0,
    "quantity":"1 kg",
    "delivery_time":"14 Mins"
  },
  {
    "platform":"BlinkIt",
    "product":"Aashirvaad Iodized Natural Salt 1 kg",
    "brand":"Aashirvaad",
    "mrp":30.0,
    "offer_price":29.0,
    "quantity":"1 kg",
    "delivery_time":"11 Mins"
  },
  {
    "platform":"DMart",
    "product":"Tata Salt - Iron Health ",
    "brand":"Tata",
    "mrp":50.0,
    "offer_price":43.0,
    "quantity":"1 kg",
    "delivery_time":"4PM-6PM"
  },
  {
    "platform":"Swiggy",
    "product":"Supreme Harvest Crystal Sugar 1 kg + Aashirvaad Iodized Salt 1 kg",
    "brand":"Supreme Harvest",
    "mrp":110.0,
    "offer_price":75.0,
    "quantity":"1 combo",
    "delivery_time":"14 Mins"
  },
  {
    "platform":"BlinkIt",
    "product":"True Story Himalayan Pink Salt \/ Sendha Namak",
    "brand":"True Story",
    "mrp":110.0,
    "offer_price":78.0,
    "quantity":"1 kg",
    "delivery_time":"11 Mins"
  },
  {
    "platform":"Swiggy",
    "product":"TRUEFARM Himalayan Pink Salt",
    "brand":"TRUEFARM",
    "mrp":110.0,
    "offer_price":89.0,
    "quantity":"500 g",
    "delivery_time":"14 Mins"
  },
  {
    "platform":"Swiggy",
    "product":"Sugar Free Gold",
    "brand":"Sugar Free",
    "mrp":320.0,
    "offer_price":320.0,
    "quantity":"50 g",
    "delivery_time":"14 Mins"
  },
  {
    "platform":"BlinkIt",
    "product":"Catch Premium Pink Rock Salt \/ Sendha Namak (Sendha Namak)",
    "brand":"Catch",
    "mrp":130.0,
    "offer_price":88.0,
    "quantity":"1 kg",
    "delivery_time":"11 Mins"
  },
  {
    "platform":"Swiggy",
    "product":"Catch Premium Pink Rock Salt",
    "brand":"Catch",
    "mrp":130.0,
    "offer_price":88.0,
    "quantity":"1 kg",
    "delivery_time":"14 Mins"
  },
  {
    "platform":"DMart",
    "product":"Catch Sprinklers Black Salt ",
    "brand":"Catch",
    "mrp":47.0,
    "offer_price":37.0,
    "quantity":"200 g",
    "delivery_time":"4PM-6PM"
  },
  {
    "platform":"Swiggy",
    "product":"Madhur Sugar & Tata Iodized Salt Pouch Combo",
    "brand":"Madhur",
    "mrp":95.0,
    "offer_price":82.0,
    "quantity":"1 combo",
    "delivery_time":"14 Mins"
  },
  {
    "platform":"Zepto",
    "product":"Conscious Food Rock Salt Unprocessed Pure And Natural",
    "brand":"Conscious Food",
    "mrp":69.0,
    "offer_price":65.0,
    "quantity":"500 g",
    "delivery_time":"9 Mins"
  },
  {
    "platform":"BlinkIt",
    "product":"Conscious Food Rock Salt \/ Sendha Namak",
    "brand":"Conscious Food",
    "mrp":69.0,
    "offer_price":66.0,
    "quantity":"500 g",
    "delivery_time":"11 Mins"
  },
  {
    "platform":"DMart",
    "product":"Rock Salt ",
    "brand":"",
    "mrp":78.0,
    "offer_price":39.0,
    "quantity":"1 kg",
    "delivery_time":"4PM-6PM"
  },
  {
    "platform":"Swiggy",
    "product":"Maya Black Salt",
    "brand":"Maya",
    "mrp":10.0,
    "offer_price":10.0,
    "quantity":"100 g",
    "delivery_time":"14 Mins"
  },
  {
    "platform":"BlinkIt",
    "product":"Whole Farm Premium Rock Salt (Crystal) (Sendha Namak)",
    "brand":"Whole Farm",
    "mrp":35.0,
    "offer_price":20.0,
    "quantity":"200 g",
    "delivery_time":"11 Mins"
  },
  {
    "platform":"DMart",
    "product":"Puro Healthy Salt ",
    "brand":"Puro",
    "mrp":110.0,
    "offer_price":87.0,
    "quantity":"1 Kg",
    "delivery_time":"4PM-6PM"
  },
  {
    "platform":"Swiggy",
    "product":"Himalayan Natives Himalayan Pink Salt Powder",
    "brand":"Himalayan Natives",
    "mrp":198.0,
    "offer_price":130.0,
    "quantity":"500 g x 2",
    "delivery_time":"14 Mins"
  },
  {
    "platform":"BlinkIt",
    "product":"Gutsukh Himalayan Pink Rock Salt (Sendha Namak)",
    "brand":"Gutsukh",
    "mrp":199.0,
    "offer_price":179.0,
    "quantity":"1 kg",
    "delivery_time":"11 Mins"
  },
  {
    "platform":"DMart",
    "product":"Uncle Chipps Plain Salted ",
    "brand":"Uncle Chipps",
    "mrp":50.0,
    "offer_price":30.0,
    "quantity":"80 g",
    "delivery_time":"4PM-6PM"
  },
  {
    "platform":"Swiggy",
    "product":"Urban Platter Pink Himalayan Rock Salt Powder Jar",
    "brand":"Urban Platter",
    "mrp":400.0,
    "offer_price":388.0,
    "quantity":"1.5 kg",
    "delivery_time":"14 Mins"
  },
  {
    "platform":"BlinkIt",
    "product":"Saffola Plus Salt Lite",
    "brand":"Saffola",
    "mrp":50.0,
    "offer_price":45.0,
    "quantity":"1 kg",
    "delivery_time":"11 Mins"
  },
  {
    "platform":"DMart",
    "product":"Tata Sampann Pistachios Roasted & Salted ",
    "brand":"Tata Sampann",
    "mrp":375.0,
    "offer_price":279.0,
    "quantity":"200 g",
    "delivery_time":"4PM-6PM"
  },
  {
    "platform":"BlinkIt",
    "product":"On1y Black Pepper & Pink Salt Grinder",
    "brand":"On1y",
    "mrp":139.0,
    "offer_price":128.0,
    "quantity":"80 g",
    "delivery_time":"11 Mins"
  },
  {
    "platform":"DMart",
    "product":"Beyond Snack Kerala Banana Chips Salt & Black Pepper ",
    "brand":"Beyond Snack",
    "mrp":200.0,
    "offer_price":100.0,
    "quantity":"250 g",
    "delivery_time":"4PM-6PM"
  },
  {
    "platform":"Swiggy",
    "product":"Catch Black Salt (Sprinkler)",
    "brand":"Catch",
    "mrp":94.0,
    "offer_price":90.0,
    "quantity":"200 g x 2",
    "delivery_time":"14 Mins"
  },
  {
    "platform":"BlinkIt",
    "product":"Bliss of Earth Himalayan Pink Salt, Natural Rock Salt \/ Sendha Namak",
    "brand":"Bliss of Earth",
    "mrp":490.0,
    "offer_price":175.0,
    "quantity":"1 kg",
    "delivery_time":"11 Mins"
  },
  {
    "platform":"DMart",
    "product":"Prov Select California Pistachio Roasted & Salted ",
    "brand":"ProV",
    "mrp":1499.0,
    "offer_price":759.0,
    "quantity":"750 g",
    "delivery_time":"4PM-6PM"
  },
  {
    "platform":"Swiggy",
    "product":"Catch Black Salt (Sprinkler)",
    "brand":"Catch",
    "mrp":47.0,
    "offer_price":47.0,
    "quantity":"200 g",
    "delivery_time":"14 Mins"
  },
  {
    "platform":"BlinkIt",
    "product":"Pro Nature Classic Pink Salt",
    "brand":"Pro Nature",
    "mrp":68.0,
    "offer_price":56.0,
    "quantity":"500 g",
    "delivery_time":"11 Mins"
  },
  {
    "platform":"DMart",
    "product":"Soulflower Aroma Therapy Lavender Bath Salt ",
    "brand":"Soulflower",
    "mrp":450.0,
    "offer_price":225.0,
    "quantity":"500 gm",
    "delivery_time":"4PM-6PM"
  },
  {
    "platform":"Swiggy",
    "product":"24 Mantra Natural Saindhava Lavana Powder Rock Salt (Sendha Namak)",
    "brand":"24 Mantra",
    "mrp":240.0,
    "offer_price":168.0,
    "quantity":"1 kg x 2",
    "delivery_time":"14 Mins"
  },
  {
    "platform":"DMart",
    "product":"Taali Roasted Peanuts - Salted ",
    "brand":"Taali",
    "mrp":80.0,
    "offer_price":20.0,
    "quantity":"150 g",
    "delivery_time":"4PM-6PM"
  },
  {
    "platform":"Swiggy",
    "product":"24 Mantra Natural Saindhava Lavana Powder Rock Salt (Sendha Namak)",
    "brand":"24 Mantra",
    "mrp":120.0,
    "offer_price":98.0,
    "quantity":"1 kg",
    "delivery_time":"14 Mins"
  },
  {
    "platform":"DMart",
    "product":"Makino Roasted Peanuts Salted ",
    "brand":"Makino",
    "mrp":100.0,
    "offer_price":50.0,
    "quantity":"150 g",
    "delivery_time":"4PM-6PM"
  },
  {
    "platform":"DMart",
    "product":"DMart Premia Cashews Salted ",
    "brand":"DMart Premia",
    "mrp":240.0,
    "offer_price":120.0,
    "quantity":"100 g",
    "delivery_time":"4PM-6PM"
  },
  {
    "platform":"Swiggy",
    "product":"Praakritik Natural Himalayan Pink Salt",
    "brand":"Praakritik",
    "mrp":150.0,
    "offer_price":117.0,
    "quantity":"500 g",
    "delivery_time":"14 Mins"
  },
  {
    "platform":"DMart",
    "product":"DMart Premia Almonds Salted ",
    "brand":"DMart Premia",
    "mrp":230.0,
    "offer_price":115.0,
    "quantity":"100 g",
    "delivery_time":"4PM-6PM"
  },
  {
    "platform":"DMart",
    "product":"Nutraj Roasted & Salted Pistachio Inshell ",
    "brand":"Nutraj",
    "mrp":1499.0,
    "offer_price":849.0,
    "quantity":"750 g",
    "delivery_time":"4PM-6PM"
  },
  {
    "platform":"DMart",
    "product":"Garden Potato Chips - Premium Salted ",
    "brand":"Garden",
    "mrp":85.0,
    "offer_price":50.0,
    "quantity":"170 gm",
    "delivery_time":"4PM-6PM"
  },
  {
    "platform":"DMart",
    "product":"Charliee Plain Salted Peanuts ",
    "brand":"Charliee",
    "mrp":110.0,
    "offer_price":55.0,
    "quantity":"180 g",
    "delivery_time":"4PM-6PM"
  },
  {
    "platform":"DMart",
    "product":"Jabsons Roasted Peanuts Classic Salted ",
    "brand":"Jabsons",
    "mrp":70.0,
    "offer_price":56.0,
    "quantity":"160 g",
    "delivery_time":"4PM-6PM"
  },
  {
    "platform":"DMart",
    "product":"Tong Garden Salted Peanuts ",
    "brand":"Tong Garden",
    "mrp":150.0,
    "offer_price":120.0,
    "quantity":"150 g",
    "delivery_time":"4PM-6PM"
  },
  {
    "platform":"DMart",
    "product":"Satyam Pumpkin Seeds Salted ",
    "brand":"Satyam",
    "mrp":121.0,
    "offer_price":114.0,
    "quantity":"100 g",
    "delivery_time":"4PM-6PM"
  },
  {
    "platform":"DMart",
    "product":"Makhanawala's Roasted Salt-N-Pepper Foxnuts ",
    "brand":"Makhanawala's",
    "mrp":150.0,
    "offer_price":115.0,
    "quantity":"60 g",
    "delivery_time":"4PM-6PM"
  },
  {
    "platform":"DMart",
    "product":"KMK Pista Salted Irani (Pistachios) ",
    "brand":"Kanji Manji Kothari",
    "mrp":319.0,
    "offer_price":255.0,
    "quantity":"200 g",
    "delivery_time":"4PM-6PM"
  },
  {
    "platform":"DMart",
    "product":"Colgate Active Salt Neem Toothpaste ",
    "brand":"Colgate",
    "mrp":348.0,
    "offer_price":195.0,
    "quantity":"400 g",
    "delivery_time":"4PM-6PM"
  },
  {
    "platform":"DMart",
    "product":"Wonderland Roasted & Salted California Pista ",
    "brand":"Wonderland",
    "mrp":725.0,
    "offer_price":389.0,
    "quantity":"400 g",
    "delivery_time":"4PM-6PM"
  },
  {
    "platform":"DMart",
    "product":"Farmley Himalayan Salted Makhana Jar ",
    "brand":"Farmley",
    "mrp":259.0,
    "offer_price":205.0,
    "quantity":"83 g",
    "delivery_time":"4PM-6PM"
  },
  {
    "platform":"DMart",
    "product":"Act II Classic Salted Popcorn ",
    "brand":"Act II",
    "mrp":10.0,
    "offer_price":9.0,
    "quantity":"30 g",
    "delivery_time":"4PM-6PM"
  },
  {
    "platform":"DMart",
    "product":"Balaji Wafers Simply Salted ",
    "brand":"Balaji",
    "mrp":40.0,
    "offer_price":36.0,
    "quantity":"135 g",
    "delivery_time":"4PM-6PM"
  },
  {
    "platform":"DMart",
    "product":"Chheda's Golden Potato Chips - Lightly Salted ",
    "brand":"Chheda's",
    "mrp":90.0,
    "offer_price":55.0,
    "quantity":"170 gm",
    "delivery_time":"4PM-6PM"
  },
  {
    "platform":"DMart",
    "product":"Chheda's Salt-N-Pepper Banana Chips ",
    "brand":"Chheda's",
    "mrp":85.0,
    "offer_price":42.0,
    "quantity":"170 gm",
    "delivery_time":"4PM-6PM"
  },
  {
    "platform":"DMart",
    "product":"Lay's Classic Salted Potato Chips ",
    "brand":"Lay's",
    "mrp":50.0,
    "offer_price":39.0,
    "quantity":"82 g",
    "delivery_time":"4PM-6PM"
  },
  {
    "platform":"DMart",
    "product":"Colgate Active Salt Toothpaste ",
    "brand":"Colgate",
    "mrp":216.0,
    "offer_price":183.0,
    "quantity":"300 g",
    "delivery_time":"4PM-6PM"
  },
  {
    "platform":"DMart",
    "product":"Makhanawala's Roasted Makhana (Foxnuts) Himalayan Pink Salt ",
    "brand":"Makhanawala's",
    "mrp":150.0,
    "offer_price":115.0,
    "quantity":"60 g",
    "delivery_time":"4PM-6PM"
  },
  {
    "platform":"DMart",
    "product":"Makhanawala's Roasted Makhana (Foxnuts) Spicy Black Salt ",
    "brand":"Makhanawala's",
    "mrp":150.0,
    "offer_price":115.0,
    "quantity":"60 g",
    "delivery_time":"4PM-6PM"
  },
  {
    "platform":"DMart",
    "product":"4700 BC Himalayan Salt Caramel Popcorn ",
    "brand":"4700 BC",
    "mrp":49.0,
    "offer_price":24.0,
    "quantity":"60 g",
    "delivery_time":"4PM-6PM"
  },
  {
    "platform":"DMart",
    "product":"ProV Select California Roasted & Salted Pistachios ",
    "brand":"ProV",
    "mrp":799.0,
    "offer_price":429.0,
    "quantity":"400 g",
    "delivery_time":"4PM-6PM"
  },
  {
    "platform":"DMart",
    "product":"Eno Fruit Salt Regular ",
    "brand":"Eno",
    "mrp":185.0,
    "offer_price":170.0,
    "quantity":"100 g",
    "delivery_time":"4PM-6PM"
  },
  {
    "platform":"DMart",
    "product":"Soulflower Rose Geranium Bath Salt ",
    "brand":"Soulflower",
    "mrp":450.0,
    "offer_price":225.0,
    "quantity":"500 gm",
    "delivery_time":"4PM-6PM"
  },
  {
    "platform":"DMart",
    "product":"Giffy Lemon & Active Salt Dish Wash Gel ",
    "brand":"Giffy",
    "mrp":239.0,
    "offer_price":119.0,
    "quantity":"900 ml",
    "delivery_time":"4PM-6PM"
  },
  {
    "platform":"DMart",
    "product":"Eno Fruit Salt Lemon Flavour ",
    "brand":"Eno",
    "mrp":185.0,
    "offer_price":165.0,
    "quantity":"100 g",
    "delivery_time":"4PM-6PM"
  },
  {
    "platform":"DMart",
    "product":"Satyam Sindhav Powder ",
    "brand":"Satyam",
    "mrp":14.0,
    "offer_price":13.0,
    "quantity":"100 g",
    "delivery_time":"4PM-6PM"
  },
  {
    "platform":"DMart",
    "product":"Avanti Sugar Cubes ",
    "brand":"Avanti",
    "mrp":65.0,
    "offer_price":59.0,
    "quantity":"126 Cubes",
    "delivery_time":"4PM-6PM"
  },
  {
    "platform":"DMart",
    "product":"Premium Jaggery ",
    "brand":"",
    "mrp":90.0,
    "offer_price":71.0,
    "quantity":"900 g",
    "delivery_time":"4PM-6PM"
  },
  {
    "platform":"DMart",
    "product":"Jaggery ",
    "brand":"",
    "mrp":90.0,
    "offer_price":74.0,
    "quantity":"900 g",
    "delivery_time":"4PM-6PM"
  },
  {
    "platform":"DMart",
    "product":"Satyam Jaggery ",
    "brand":"Satyam",
    "mrp":60.0,
    "offer_price":55.0,
    "quantity":"500 gm",
    "delivery_time":"4PM-6PM"
  },
  {
    "platform":"DMart",
    "product":"Sugar Free Natura Pellets ",
    "brand":"Sugar Free",
    "mrp":320.0,
    "offer_price":280.0,
    "quantity":"500 Pellets",
    "delivery_time":"4PM-6PM"
  },
  {
    "platform":"DMart",
    "product":"DMart Premia Sakariya ",
    "brand":"DMart Premia",
    "mrp":23.0,
    "offer_price":16.0,
    "quantity":"200 g",
    "delivery_time":"4PM-6PM"
  },
  {
    "platform":"DMart",
    "product":"Keshar Premium Natural Jaggery Jar ",
    "brand":"Keshar",
    "mrp":125.0,
    "offer_price":102.0,
    "quantity":"800 g",
    "delivery_time":"4PM-6PM"
  },
  {
    "platform":"DMart",
    "product":"Satyam Sugar Bura ",
    "brand":"Satyam",
    "mrp":42.0,
    "offer_price":39.0,
    "quantity":"500 gm",
    "delivery_time":"4PM-6PM"
  },
  {
    "platform":"DMart",
    "product":"Pitambari Ruchiyana Jaggery Powder ",
    "brand":"Pitambari",
    "mrp":85.0,
    "offer_price":51.0,
    "quantity":"500 gm",
    "delivery_time":"4PM-6PM"
  },
  {
    "platform":"DMart",
    "product":"Nutrivalue Stevia Leaves - Natural Sweetener ",
    "brand":"Nutrivalue",
    "mrp":150.0,
    "offer_price":110.0,
    "quantity":"50 g",
    "delivery_time":"4PM-6PM"
  },
  {
    "platform":"DMart",
    "product":"Organic Tattva Jaggery Powder ",
    "brand":"Organic Tattva",
    "mrp":90.0,
    "offer_price":65.0,
    "quantity":"500 gm",
    "delivery_time":"4PM-6PM"
  },
  {
    "platform":"DMart",
    "product":"Organic Tattva Brown Sugar ",
    "brand":"Organic Tattva",
    "mrp":90.0,
    "offer_price":72.0,
    "quantity":"500 gm",
    "delivery_time":"4PM-6PM"
  },
  {
    "platform":"DMart",
    "product":"DMart Premia Big Sakariya ",
    "brand":"DMart Premia",
    "mrp":21.0,
    "offer_price":15.0,
    "quantity":"200 g",
    "delivery_time":"4PM-6PM"
  },
  {
    "platform":"DMart",
    "product":"Sugar Free Green Stevia Powder ",
    "brand":"Sugar Free",
    "mrp":275.0,
    "offer_price":235.0,
    "quantity":"200 g",
    "delivery_time":"4PM-6PM"
  },
  {
    "platform":"DMart",
    "product":"Rasmalai Premium Desi Jaggery Pieces ",
    "brand":"Rasmalai",
    "mrp":100.0,
    "offer_price":89.0,
    "quantity":"800 g",
    "delivery_time":"4PM-6PM"
  },
  {
    "platform":"DMart",
    "product":"Shree Annapurna Jaggery Powder ",
    "brand":"Annapurna",
    "mrp":100.0,
    "offer_price":61.0,
    "quantity":"1 Kg",
    "delivery_time":"4PM-6PM"
  },
  {
    "platform":"DMart",
    "product":"Bebe Solid Cane Jaggery ",
    "brand":"Cremica",
    "mrp":170.0,
    "offer_price":125.0,
    "quantity":"1 kg",
    "delivery_time":"4PM-6PM"
  },
  {
    "platform":"DMart",
    "product":"Bebe Cardamom Jaggery ",
    "brand":"Bebe",
    "mrp":100.0,
    "offer_price":75.0,
    "quantity":"250 g",
    "delivery_time":"4PM-6PM"
  },
  {
    "platform":"DMart",
    "product":"Swarnaras Jaggery Bites ",
    "brand":"Swarnaras",
    "mrp":110.0,
    "offer_price":57.0,
    "quantity":"500 gm",
    "delivery_time":"4PM-6PM"
  },
  {
    "platform":"DMart",
    "product":"Jivana Jaggery Powder Jar ",
    "brand":"Jivana",
    "mrp":120.0,
    "offer_price":75.0,
    "quantity":"500 g",
    "delivery_time":"4PM-6PM"
  },
  {
    "platform":"DMart",
    "product":"Organic India Jaggery Powder ",
    "brand":"Organic India",
    "mrp":110.0,
    "offer_price":99.0,
    "quantity":"500 g",
    "delivery_time":"4PM-6PM"
  },
  {
    "platform":"DMart",
    "product":"DMart Premia Sugar ",
    "brand":"DMart Premia",
    "mrp":305.0,
    "offer_price":249.0,
    "quantity":"5 kg",
    "delivery_time":"4PM-6PM"
  },
  {
    "platform":"DMart",
    "product":"Organic Tattva Sugar ",
    "brand":"Organic Tattva",
    "mrp":160.0,
    "offer_price":99.0,
    "quantity":"1 kg",
    "delivery_time":"4PM-6PM"
  },
  {
    "platform":"DMart",
    "product":"Sugar Free Gold Pellets ",
    "brand":"Sugar Free",
    "mrp":320.0,
    "offer_price":280.0,
    "quantity":"500 Pellets",
    "delivery_time":"4PM-6PM"
  },
  {
    "platform":"DMart",
    "product":"DMart Premia Sugar Crystals (Khadi Shakkar) ",
    "brand":"DMart Premia",
    "mrp":25.0,
    "offer_price":17.0,
    "quantity":"200 g",
    "delivery_time":"4PM-6PM"
  },
  {
    "platform":"DMart",
    "product":"Paawak Jaggery Cubes Jar ",
    "brand":"Paawak",
    "mrp":110.0,
    "offer_price":55.0,
    "quantity":"500 gm",
    "delivery_time":"4PM-6PM"
  },
  {
    "platform":"DMart",
    "product":"DMart Premia Sugar Candy ",
    "brand":"DMart Premia",
    "mrp":33.0,
    "offer_price":24.0,
    "quantity":"200 g",
    "delivery_time":"4PM-6PM"
  },
  {
    "platform":"DMart",
    "product":"Madhur Pure & Hygienic Sugar ",
    "brand":"Madhur",
    "mrp":315.0,
    "offer_price":266.0,
    "quantity":"5 kg",
    "delivery_time":"4PM-6PM"
  },
  {
    "platform":"DMart",
    "product":"Sugar Free D'Lite Choco Chip Cookies ",
    "brand":"Sugar Free",
    "mrp":65.0,
    "offer_price":49.0,
    "quantity":"75 g",
    "delivery_time":"4PM-6PM"
  },
  {
    "platform":"DMart",
    "product":"Sugar Free D'Lite Yummy Berry Cookies ",
    "brand":"Sugar Free",
    "mrp":65.0,
    "offer_price":49.0,
    "quantity":"75 g",
    "delivery_time":"4PM-6PM"
  },
  {
    "platform":"DMart",
    "product":"Sugar Free D'Lite Mocha Hazelnut Cookies ",
    "brand":"Sugar Free",
    "mrp":65.0,
    "offer_price":49.0,
    "quantity":"75 g",
    "delivery_time":"4PM-6PM"
  },
  {
    "platform":"DMart",
    "product":"Happy Family Bingo Multi Utility Set (Grey) ",
    "brand":"Happy Family",
    "mrp":199.0,
    "offer_price":99.0,
    "quantity":"1 U",
    "delivery_time":"4PM-6PM"
  },
  {
    "platform":"DMart",
    "product":"Happy Family Aroma Multi Utility Set (Grey) ",
    "brand":"Happy Family",
    "mrp":229.0,
    "offer_price":129.0,
    "quantity":"1 U",
    "delivery_time":"4PM-6PM"
  },
  {
    "platform":"DMart",
    "product":"Happy Family Woodland Multi Utility Set (Wood Colour ) ",
    "brand":"Happy Family",
    "mrp":349.0,
    "offer_price":199.0,
    "quantity":"1 U",
    "delivery_time":"4PM-6PM"
  },
  {
    "platform":"DMart",
    "product":"Milky Mist Table Butter Chiplet ",
    "brand":"Milky Mist",
    "mrp":78.0,
    "offer_price":57.0,
    "quantity":"10x10 g",
    "delivery_time":"4PM-6PM"
  },
  {
    "platform":"DMart",
    "product":"D Homes Steel Sprinkler Glass ",
    "brand":"D Homes",
    "mrp":135.0,
    "offer_price":119.0,
    "quantity":"1 Unit",
    "delivery_time":"4PM-6PM"
  },
  {
    "platform":"DMart",
    "product":"Swad Refined Soyabean Oil Pouch (1 L) ",
    "brand":"Swad",
    "mrp":160.0,
    "offer_price":137.0,
    "quantity":"910 g",
    "delivery_time":"4PM-6PM"
  },
  {
    "platform":"DMart",
    "product":"DMart Premia Refined Rice Bran Oil (1 L) ",
    "brand":"DMart Premia",
    "mrp":155.0,
    "offer_price":134.0,
    "quantity":"910 g",
    "delivery_time":"4PM-6PM"
  },
  {
    "platform":"DMart",
    "product":"Joyo Better Home Tuff Patla - Big (Grey) ",
    "brand":"Joyo",
    "mrp":1216.0,
    "offer_price":599.0,
    "quantity":"1 Unit",
    "delivery_time":"4PM-6PM"
  },
  {
    "platform":"DMart",
    "product":"Joyo Better Home Sqaure Printed Patla - Medium (Grey) ",
    "brand":"Joyo",
    "mrp":947.0,
    "offer_price":399.0,
    "quantity":"Grey",
    "delivery_time":"4PM-6PM"
  },
  {
    "platform":"DMart",
    "product":"Joyo Better Home Sqaure Printed Patla - Medium (Blue) ",
    "brand":"Joyo",
    "mrp":947.0,
    "offer_price":399.0,
    "quantity":"Blue",
    "delivery_time":"4PM-6PM"
  },
  {
    "platform":"DMart",
    "product":"Geep Dewlike Table Lamp With Bulb ",
    "brand":"Geep",
    "mrp":1499.0,
    "offer_price":299.0,
    "quantity":"1 Unit",
    "delivery_time":"4PM-6PM"
  }
]